{
  "tag": "2025-01-25_162009",
  "event": {
    "event_type": "touch",
    "log_lines": null,
    "x": null,
    "y": null,
    "view": {
      "package": "com.example.chatter",
      "visible": true,
      "checkable": false,
      "child_count": 0,
      "editable": false,
      "clickable": false,
      "is_password": false,
      "focusable": false,
      "enabled": true,
      "content_description": null,
      "children": [],
      "focused": false,
      "bounds": [
        [
          77,
          812
        ],
        [
          296,
          870
        ]
      ],
      "resource_id": null,
      "checked": false,
      "text": "Username : ",
      "class": "android.widget.TextView",
      "scrollable": false,
      "selected": false,
      "long_clickable": false,
      "parent": 10,
      "temp_id": 12,
      "size": "219*58",
      "signature": "[class]android.widget.TextView[resource_id]None[text]Username : [enabled,,]",
      "view_str": "a81bc1490f79cedf5cfea306a2efe6a9",
      "content_free_signature": "[class]android.widget.TextView[resource_id]None",
      "allowed_actions": [
        "touch"
      ],
      "special_attrs": [],
      "local_id": "2",
      "desc": "<p bound_box=77,812,296,870>Username : </p>"
    }
  },
  "start_state": "057046f1023140184007fcfa477f9985",
  "stop_state": "057046f1023140184007fcfa477f9985",
  "event_str": "TouchEvent(state=057046f1023140184007fcfa477f9985, view=a81bc1490f79cedf5cfea306a2efe6a9(RegistrationPage/TextView-Username :))"
}